yai_nexus_logger/__init__.py
yai_nexus_logger/configurator.py
yai_nexus_logger/core.py
yai_nexus_logger/trace_context.py
yai_nexus_logger/uvicorn_support.py
yai_nexus_logger/internal/internal_formatter.py
yai_nexus_logger/internal/internal_handlers.py
yai_nexus_logger/internal/internal_settings.py
yai_nexus_logger/internal/internal_sls_handler.py
yai_nexus_logger/internal/internal_utils.py
yai_nexus_logger-0.4.0.dist-info/licenses/LICENSE
yai_nexus_logger-0.4.0.dist-info/METADATA
yai_nexus_logger-0.4.0.dist-info/WHEEL
yai_nexus_logger-0.4.0.dist-info/top_level.txt
yai_nexus_logger-0.4.0.dist-info/RECORD
