Metadata-Version: 2.4
Name: yai-nexus-logger
Version: 0.4.0
Summary: A powerful, structured logger for modern Python applications, with built-in trace_id support for easy request tracking.
Author-email: Harry <harrytang.next@gmail.com>
Project-URL: Homepage, https://github.com/yai-nexus/yai-nexus-logger
Project-URL: Bug Tracker, https://github.com/yai-nexus/yai-nexus-logger/issues
Classifier: Programming Language :: Python :: 3
Classifier: License :: OSI Approved :: MIT License
Classifier: Operating System :: OS Independent
Requires-Python: >=3.10
License-File: LICENSE
Provides-Extra: dev
Requires-Dist: pytest; extra == "dev"
Requires-Dist: pytest-cov; extra == "dev"
Requires-Dist: pytest-mock; extra == "dev"
Requires-Dist: ruff==0.12.1; extra == "dev"
Requires-Dist: fastapi; extra == "dev"
Requires-Dist: uvicorn[standard]; extra == "dev"
Requires-Dist: httpx; extra == "dev"
Requires-Dist: python-dotenv; extra == "dev"
Provides-Extra: sls
Requires-Dist: aliyun-log-python-sdk>=0.6.45; extra == "sls"
Dynamic: license-file
